Workbook

Sheet Roadmap produit
A1: ekho — Roadmap Produit & Monetisation
A2: Etape | B2: Roadmap produit | C2: Monetisation | D2: Objectifs
A3: T1 — MVP | B3: Recommandation lieux selon le mood, onboarding, partenaires gratuits | C3: Aucune | D3: Valider l'usage, recruter premiers utilisateurs & partenaires
A4: T2 — Lancement | B4: Affluence lieux, presence anonyme, favoris, fiches partenaires | C4: Starter 49 EUR/mois | D4: 10 000 utilisateurs, 40 partenaires
A5: T3 — Premium v1 | B5: Recherche avancee, recherches illimitees, filtres avances | C5: Plus 4,99 EUR/mois | D5: 1,2 % de conversion payante
A6: T4 — Premium v2 | B6: Recommandations IA, notifications intelligentes, suggestions contextuelles | C6: Premium 15 EUR/mois | D6: 2 % de conversion payante
A7: Annee 2 | B7: Promotions ciblees, gestion heures creuses, analytics partenaires | C7: Growth 99 EUR/mois | D7: Conversion des partenaires gratuits
A8: Annee 3 | B8: IA predictive, analyses avancees, benchmark, reco business | C8: Insight 199 EUR/mois | D8: Forte hausse de l'ARPU partenaires
A9: Annee 4+ | B9: Multi-villes, IA temps reel, API, offres Enterprise | C9: Enterprise | D9: Changement d'echelle

Sheet Projections financieres
A1: ekho — Projections Financieres 5 ans
A2: Hypotheses (cellules bleues = inputs modifiables)
B3: An 1 | C3: An 2 | D3: An 3 | E3: An 4 | F3: An 5 | G3: Notes
A4: UTILISATEURS
A5: Utilisateurs totaux | B5: 10000 | C5: 35000 | D5: 100000 | E5: 250000 | F5: 500000 | G5: Source: objectifs BP
A6: dont Gratuit | B6: =B5-B7-B8 -> 9800 | C6: =C5-C7-C8 -> 33250 | D6: =D5-D7-D8 -> 95000 | E6: =E5-E7-E8 -> 237500 | F6: =F5-F7-F8 -> 475000 | G6: Totaux - Plus - Premium
A7: dont Plus (4,99 EUR) | B7: 120 | C7: 1050 | D7: 3000 | E7: 7500 | F7: 15000 | G7: 1,2% -> 3% -> 4%
A8: dont Premium (15 EUR) | B8: 80 | C8: 700 | D8: 2000 | E8: 5000 | F8: 10000 | G8: 0,8% -> 2% -> 3%
A9: CA B2C mensuel (EUR) | B9: =B7*4.99+B8*15 -> 1798.8 | C9: =C7*4.99+C8*15 -> 15739.5 | D9: =D7*4.99+D8*15 -> 44970 | E9: =E7*4.99+E8*15 -> 112425 | F9: =F7*4.99+F8*15 -> 224850 | G9: Plus*4,99 + Premium*15
A10: CA B2C annuel (EUR) | B10: =B9*12 -> 21585.6 | C10: =C9*12 -> 188874 | D10: =D9*12 -> 539640 | E10: =E9*12 -> 1349100 | F10: =F9*12 -> 2698200 | G10: Mensuel * 12
A12: PARTENAIRES
A13: Partenaires totaux | B13: 40 | C13: 120 | D13: 400 | E13: 900 | F13: 1500 | G13: Trajectoire prudente
A14: dont Gratuit | B14: 28 | C14: 60 | D14: 160 | E14: 360 | F14: 600
A15: dont Starter (49 EUR) | B15: 6 | C15: 24 | D15: 80 | E15: 180 | F15: 300
A16: dont Growth (99 EUR) | B16: 4 | C16: 24 | D16: 96 | E16: 270 | F16: 450
A17: dont Insight (199 EUR) | B17: 2 | C17: 12 | D17: 64 | E17: 90 | F17: 150
A18: CA B2B mensuel (EUR) | B18: =B15*49+B16*99+B17*199 -> 1088 | C18: =C15*49+C16*99+C17*199 -> 5940 | D18: =D15*49+D16*99+D17*199 -> 26160 | E18: =E15*49+E16*99+E17*199 -> 53460 | F18: =F15*49+F16*99+F17*199 -> 89100 | G18: Starter*49 + Growth*99 + Insight*199
A19: CA B2B annuel (EUR) | B19: =B18*12 -> 13056 | C19: =C18*12 -> 71280 | D19: =D18*12 -> 313920 | E19: =E18*12 -> 641520 | F19: =F18*12 -> 1069200 | G19: Mensuel * 12
A21: TOTAL
A22: CA mensuel total (EUR) | B22: =B9+B18 -> 2886.8 | C22: =C9+C18 -> 21679.5 | D22: =D9+D18 -> 71130 | E22: =E9+E18 -> 165885 | F22: =F9+F18 -> 313950 | G22: B2C mensuel + B2B mensuel
A23: CA annuel total (EUR) | B23: =B10+B19 -> 34641.6 | C23: =C10+C19 -> 260154 | D23: =D10+D19 -> 853560 | E23: =E10+E19 -> 1990620 | F23: =F10+F19 -> 3767400 | G23: B2C annuel + B2B annuel
A25: GEOGRAPHIE
A26: Villes couvertes | B26: 1 | C26: 3 | D26: 8 | E26: 15 | F26: 25
A27: Partenaires / ville (moy) | B27: =IFERROR(B13/B26,0) -> 40 | C27: =IFERROR(C13/C26,0) -> 40 | D27: =IFERROR(D13/D26,0) -> 50 | E27: =IFERROR(E13/E26,0) -> 60 | F27: =IFERROR(F13/F26,0) -> 60 | G27: Partenaires / Villes

Sheet Pricing Utilisateurs
A1: ekho — Offres Utilisateurs
A2: Fonctionnalite | B2: Gratuit | C2: Plus — 4,99 EUR/mois | D2: Premium — 9,99 à 14,99 EUR/mois (à tester)
A3: Recommandations selon le mood | B3: Oui | C3: Oui | D3: Oui
A4: Propositions de lieux / recherche | B4: 3 | D4: Illimitees
A5: Recherches / jour | B5: 2 | D5: Illimitees
A6: Voir l'ambiance du lieu | B6: Oui | C6: Oui | D6: Oui
A7: Voir l'affluence estimee | B7: Oui | C7: Oui | D7: Oui
A8: Voir les personnes ouvertes a echanger | B8: non | C8: Oui | D8: Oui
A9: Favoris | B9: non | C9: Oui | D9: Oui
A10: Recherche IA langage naturel | B10: - | C10: Oui | D10: Oui
A11: Filtres avances (terrasse, wifi...) | B11: - | C11: Oui | D11: Oui
A12: Historique & collections | B12: - | C12: Oui | D12: Oui
A13: Acces anticipe aux nouveautes | B13: - | C13: Oui | D13: Oui
A14: Recherches illimitees | B14: - | C14: - | D14: Oui
A15: Signaux détaillés de présence via ekho | B15: - | C15: - | D15: Oui
A16: Affluence temps reel precise | B16: - | C16: - | D16: Oui
A17: Recommandations IA proactives | B17: - | C17: - | D17: Oui
... A22: Point de vigilance | B22: Le gratuit doit suffire à créer l'habitude | C22: Plus doit réduire la friction | D22: Premium doit rester optionnel
A23: Proposition Revenu | B23: Pas d'abonnement / Paiement de token / consommation du scan.

Sheet Pricing Lieux
A1: ekho — Offres Lieux Partenaires
A2: Fonctionnalite | B2: Gratuit | C2: Starter — 49 EUR/mois | D2: Growth — 99 EUR/mois | E2: Insight — 199 EUR/mois
A3: Presence sur ekho | B3: Oui | C3: Oui | D3: Oui | E3: Oui
A4: Fiche etablissement (photos, horaires) | B4: Oui | C4: Oui | D4: Oui | E4: Oui
A5: Apparition dans les recommandations | B5: Oui | C5: Oui | D5: Oui | E5: Oui
A6: Modifier les informations du lieu | B6: - | C6: Oui | D6: Oui | E6: Oui
A7: Gestion photos & evenements | B7: - | C7: Oui | D7: Oui | E7: Oui
A8: Campagnes locales / heures creuses (sans modifier le ranking) | B8: - | C8: Basique | D8: Avancee | E8: Prioritaire mais separee des recommandations neutres
A9: Statistiques de base (vues, clics) | B9: - | C9: Oui | D9: Oui | E9: Oui
A10: Mise a jour ambiance temps reel | B10: - | C10: - | D10: Oui | E10: Oui
A11: Promotions ciblees & Happy Hours | B11: - | C11: - | D11: Oui | E11: Oui
A12: Mise en avant heures creuses auto | B12: - | C12: - | D12: Oui | E12: Oui
A13: Nombre de visites generees | B13: - | C13: - | D13: Oui | E13: Oui
... A24: Risque a eviter | B24: Transformer ekho en annuaire sponsorise | C24: Perdre la confiance | D24: Baisser la qualite percue | E24: Detruire la defensibilite

Sheet Trajectoire geographique
A1: ekho — Trajectoire Geographique (objectifs prudents)
A2: Annee | B2: Villes | C2: Partenaires | D2: Partenaires / ville (moy) | E2: Notes
A3: An 1 | B3: 1 | C3: 40 | D3: =IFERROR(C3/B3,0) -> 40 | E3: Marseille — MVP & validation usage
A4: An 2 | B4: 3 | C4: 120 | D4: =IFERROR(C4/B4,0) -> 40 | E4: + Lyon, Bordeaux
A5: An 3 | B5: 8 | C5: 400 | D5: =IFERROR(C5/B5,0) -> 50 | E5: + Paris, Toulouse, Nice, Nantes, Lille
A6: An 4 | B6: 15 | C6: 900 | D6: =IFERROR(C6/B6,0) -> 60 | E6: Couverture nationale dense
A7: An 5 | B7: 25 | C7: 1500 | D7: =IFERROR(C7/B7,0) -> 60 | E7: Saturation principale FR, preparer export EU

Sheet Vision & These
A1: ekho — Vision, these et moat
A3: These centrale | B3: ekho construit la carte vivante des moods, des lieux et des presences en ville. | D3: Phase | E3: Objectif | F3: Critere de passage
A4: Formulation faible | B4: Une app qui recommande des lieux selon ton mood. | D4: 0-90 jours | E4: Prouver l'usage a Marseille | F4: 30% des sessions menent a une action
A5: Formulation forte | B5: Une infrastructure locale qui comprend ou les gens veulent aller, a quel moment, dans quel etat d'esprit, et dans quels lieux la ville est vraiment vivante. | D5: 3-6 mois | E5: Prouver la densite locale | F5: 40 lieux, 10 actifs chaque semaine
D6: 6-12 mois | E6: Prouver la valeur B2B | F6: 10 lieux prets a payer apres test
A7: Ce qui doit devenir proprietaire | B7: Demandes de moods par zone et par heure | D7: Annee 2 | E7: Repliquer dans 2 villes | F7: CAC partenaire et onboarding standardises
B8: Signaux d'ambiance et d'affluence des lieux | D8: Annee 3 | E8: Creer l'avantage data | F8: Insights utiles impossibles a obtenir via Google/Instagram
B9: Presences anonymes et ouverture sociale
B10: Historique des lieux choisis, refuses, sauvegardes | D10: Ce que je ferais | E10: Je lancerais en ville unique avec densite forte avant d'elargir.
B11: Performance des lieux par moment de la semaine | D11: Ce que je ne ferais pas | E11: Je ne construirais pas l'IA avancee avant d'avoir de vrais signaux.
D12: Priorite | E12: Habitude utilisateur + activite partenaire + donnee proprietaire.
A13: Pourquoi c'est defensible | B13: La valeur vient de la densite locale et de la donnee comportementale, pas de la fiche etablissement.
A14: Risque principal | B14: Si les lieux peuvent payer pour remonter dans les recommandations, ekho perd sa promesse utilisateur.
A15: Decision produit | B15: Les recommandations restent neutres. La monetisation lieux porte sur analytics, heures creuses, campagnes separees, insights.
A17: North Star Metric | B17: Nombre de decisions de sortie reussies par semaine dans une ville donnee.
A18: KPI 1 | B18: % de sessions qui finissent par un lieu sauvegarde, appele, ouvert ou rejoint
A19: KPI 2 | B19: % de lieux partenaires actifs chaque semaine

Sheet Inputs V2
A1: ekho — Inputs modifiables V2
A3: Prix & marges | B3: Valeur | C3: Note
A4: Plus prix mensuel | B4: 4.99 | C4: Prix credible pour usage regulier
A5: Premium prix mensuel | B5: 9.99 | C5: Tester 9,99 avant 14,99/15
A6: Starter prix mensuel | B6: 49 | C6: Fiche + gestion simple
A7: Growth prix mensuel | B7: 99 | C7: Activation heures creuses + stats
A8: Insight prix mensuel | B8: 199 | C8: Analytics avancees + benchmark
A9: Marge brute B2C | B9: 0.85 | C9: App + paiement + support
A10: Marge brute B2B | B10: 0.8 | C10: Support partenaire + data ops
A11: Churn mensuel utilisateurs payants | B11: 0.04 | C11: A tester
A13: Hypotheses par annee | B13: An 1 | C13: An 2 | D13: An 3 | E13: An 4 | F13: An 5
A14: Utilisateurs actifs | B14: 10000 | C14: 35000 | D14: 100000 | E14: 250000 | F14: 500000
A15: Conversion Plus | B15: 0.012 | C15: 0.02 | D15: 0.025 | E15: 0.03 | F15: 0.035
A16: Conversion Premium | B16: 0.002 | C16: 0.005 | D16: 0.008 | E16: 0.012 | F16: 0.015
A17: Partenaires totaux | B17: 40 | C17: 120 | D17: 400 | E17: 900 | F17: 1500
A18: % Starter | B18: 0.15 | C18: 0.2 | D18: 0.2 | E18: 0.2 | F18: 0.2
A19: % Growth | B19: 0.1 | C19: 0.2 | D19: 0.24 | E19: 0.3 | F19: 0.3
A20: % Insight | B20: 0.05 | C20: 0.1 | D20: 0.16 | E20: 0.1 | F20: 0.1
A21: Villes | B21: 1 | C21: 3 | D21: 8 | E21: 15 | F21: 25
A22: Equipe / salaires annuels | B22: 90000 | C22: 180000 | D22: 360000 | E22: 700000 | F22: 1200000
A23: Marketing annuel | B23: 15000 | C23: 60000 | D23: 180000 | E23: 400000 | F23: 750000
A24: Tech + G&A annuel | B24: 25000 | C24: 60000 | D24: 120000 | E24: 250000 | F24: 450000
A25: Budget data / ops lieux | B25: 10000 | C25: 30000 | D25: 80000 | E25: 160000 | F25: 300000

Sheet Projections V2
A1: ekho — Projections V2 avec couts, churn et logique investisseur
A3: Metric | B3: An 1 | C3: An 2 | D3: An 3 | E3: An 4 | F3: An 5 | G3: Pourquoi c'est utile
A4: UTILISATEURS
A5: Utilisateurs actifs | B5: ='Inputs V2'!B14 -> 10000 | C5: ='Inputs V2'!C14 -> 35000 | D5: ='Inputs V2'!D14 -> 100000 | E5: ='Inputs V2'!E14 -> 250000 | F5: ='Inputs V2'!F14 -> 500000 | G5: Base de densite locale
A6: Conversion Plus | B6: ='Inputs V2'!B15 -> 0.012 | C6: ='Inputs V2'!C15 -> 0.02 | D6: ='Inputs V2'!D15 -> 0.025 | E6: ='Inputs V2'!E15 -> 0.03 | F6: ='Inputs V2'!F15 -> 0.035 | G6: A ne pas surestimer
A7: Conversion Premium | B7: ='Inputs V2'!B16 -> 0.002 | C7: ='Inputs V2'!C16 -> 0.005 | D7: ='Inputs V2'!D16 -> 0.008 | E7: ='Inputs V2'!E16 -> 0.012 | F7: ='Inputs V2'!F16 -> 0.015 | G7: Premium doit rester optionnel
A8: Utilisateurs Plus | B8: =B5*B6 -> 120 | C8: =C5*C6 -> 700 | D8: =D5*D6 -> 2500 | E8: =E5*E6 -> 7500 | F8: =F5*F6 -> 17500 | G8: Volume payant basique
A9: Utilisateurs Premium | B9: =B5*B7 -> 20 | C9: =C5*C7 -> 175 | D9: =D5*D7 -> 800 | E9: =E5*E7 -> 3000 | F9: =F5*F7 -> 7500 | G9: Usage intensif
A10: CA B2C mensuel | B10: =B8*'Inputs V2'!$B$4+B9*'Inputs V2'!$B$5 -> 798.6 | C10: =C8*'Inputs V2'!$B$4+C9*'Inputs V2'!$B$5 -> 5241.25 | D10: =D8*'Inputs V2'!$B$4+D9*'Inputs V2'!$B$5 -> 20467 | E10: =E8*'Inputs V2'!$B$4+E9*'Inputs V2'!$B$5 -> 67395 | F10: =F8*'Inputs V2'!$B$4+F9*'Inputs V2'!$B$5 -> 162250 | G10: MRR utilisateurs
A11: CA B2C annuel | B11: =B10*12 -> 9583.2 | C11: =C10*12 -> 62895 | D11: =D10*12 -> 245604 | E11: =E10*12 -> 808740 | F11: =F10*12 -> 1947000 | G11: ARR utilisateurs
A13: PARTENAIRES
A14: Partenaires totaux | B14: ='Inputs V2'!B17 -> 40 | C14: ='Inputs V2'!C17 -> 120 | D14: ='Inputs V2'!D17 -> 400 | E14: ='Inputs V2'!E17 -> 900 | F14: ='Inputs V2'!F17 -> 1500 | G14: Densite ville
A15: Starter | B15: =B14*'Inputs V2'!B18 -> 6 | C15: =C14*'Inputs V2'!C18 -> 24 | D15: =D14*'Inputs V2'!D18 -> 80 | E15: =E14*'Inputs V2'!E18 -> 180 | F15: =F14*'Inputs V2'!F18 -> 300 | G15: Entree B2B
A16: Growth | B16: =B14*'Inputs V2'!B19 -> 4 | C16: =C14*'Inputs V2'!C19 -> 24 | D16: =D14*'Inputs V2'!D19 -> 96 | E16: =E14*'Inputs V2'!E19 -> 270 | F16: =F14*'Inputs V2'!F19 -> 450 | G16: Offre coeur
A17: Insight | B17: =B14*'Inputs V2'!B20 -> 2 | C17: =C14*'Inputs V2'!C20 -> 12 | D17: =D14*'Inputs V2'!D20 -> 64 | E17: =E14*'Inputs V2'!E20 -> 90 | F17: =F14*'Inputs V2'!F20 -> 150 | G17: Upsell data
A18: Gratuits | B18: =B14-B15-B16-B17 -> 28 | C18: =C14-C15-C16-C17 -> 60 | D18: =D14-D15-D16-D17 -> 160 | E18: =E14-E15-E16-E17 -> 360 | F18: =F14-F15-F16-F17 -> 600 | G18: Pipeline partenaire
A19: CA B2B mensuel | B19: =B15*'Inputs V2'!$B$6+B16*'Inputs V2'!$B$7+B17*'Inputs V2'!$B$8 -> 1088 | C19: =C15*'Inputs V2'!$B$6+C16*'Inputs V2'!$B$7+C17*'Inputs V2'!$B$8 -> 5940 | D19: =D15*'Inputs V2'!$B$6+D16*'Inputs V2'!$B$7+D17*'Inputs V2'!$B$8 -> 26160 | E19: =E15*'Inputs V2'!$B$6+E16*'Inputs V2'!$B$7+E17*'Inputs V2'!$B$8 -> 53460 | F19: =F15*'Inputs V2'!$B$6+F16*'Inputs V2'!$B$7+F17*'Inputs V2'!$B$8 -> 89100 | G19: MRR lieux
A20: CA B2B annuel | B20: =B19*12 -> 13056 | C20: =C19*12 -> 71280 | D20: =D19*12 -> 313920 | E20: =E19*12 -> 641520 | F20: =F19*12 -> 1069200 | G20: ARR lieux
A22: ECONOMIE
A23: CA annuel total | B23: =B11+B20 -> 22639.2 | C23: =C11+C20 -> 134175 | D23: =D11+D20 -> 559524 | E23: =E11+E20 -> 1450260 | F23: =F11+F20 -> 3016200 | G23: Topline
A24: % CA B2B | B24: =B20/B23 -> 0.57669882 | C24: =C20/C23 -> 0.53124651 | D24: =D20/D23 -> 0.56104832 | E24: =E20/E23 -> 0.44234827 | F24: =F20/F23 -> 0.35448578 | G24: Dependance lieux
A25: Marge brute | B25: =B11*'Inputs V2'!$B$9+B20*'Inputs V2'!$B$10 -> 18590.52 | C25: =C11*'Inputs V2'!$B$9+C20*'Inputs V2'!$B$10 -> 110484.75 | D25: =D11*'Inputs V2'!$B$9+D20*'Inputs V2'!$B$10 -> 459899.4 | E25: =E11*'Inputs V2'!$B$9+E20*'Inputs V2'!$B$10 -> 1200645 | F25: =F11*'Inputs V2'!$B$9+F20*'Inputs V2'!$B$10 -> 2510310 | G25: Avant OPEX
A26: Equipe / salaires | B26: ='Inputs V2'!B22 -> 90000 | C26: ='Inputs V2'!C22 -> 180000 | D26: ='Inputs V2'!D22 -> 360000 | E26: ='Inputs V2'!E22 -> 700000 | F26: ='Inputs V2'!F22 -> 1200000 | G26: Execution produit/commerciale
A27: Marketing | B27: ='Inputs V2'!B23 -> 15000 | C27: ='Inputs V2'!C23 -> 60000 | D27: ='Inputs V2'!D23 -> 180000 | E27: ='Inputs V2'!E23 -> 400000 | F27: ='Inputs V2'!F23 -> 750000 | G27: Acquisition
A28: Tech + G&A | B28: ='Inputs V2'!B24 -> 25000 | C28: ='Inputs V2'!C24 -> 60000 | D28: ='Inputs V2'!D24 -> 120000 | E28: ='Inputs V2'!E24 -> 250000 | F28: ='Inputs V2'!F24 -> 450000 | G28: Infrastructure
A29: Data / ops lieux | B29: ='Inputs V2'!B25 -> 10000 | C29: ='Inputs V2'!C25 -> 30000 | D29: ='Inputs V2'!D25 -> 80000 | E29: ='Inputs V2'!E25 -> 160000 | F29: ='Inputs V2'!F25 -> 300000 | G29: Qualite terrain
A30: Total OPEX | B30: =SUM(B26:B29) -> 140000 | C30: =SUM(C26:C29) -> 330000 | D30: =SUM(D26:D29) -> 740000 | E30: =SUM(E26:E29) -> 1510000 | F30: =SUM(F26:F29) -> 2700000 | G30: Couts annuels
A31: EBITDA | B31: =B25-B30 -> -121409.48 | C31: =C25-C30 -> -219515.25 | D31: =D25-D30 -> -280100.6 | E31: =E25-E30 -> -309355 | F31: =F25-F30 -> -189690 | G31: Profitabilite operationnelle
A32: Besoin de cash cumule | B32: =MAX(0,-B31) -> 121409.48 | C32: =MAX(0,B32-C31) -> 340924.73 | D32: =MAX(0,C32-D31) -> 621025.33 | E32: =MAX(0,D32-E31) -> 930380.33 | F32: =MAX(0,E32-F31) -> 1120070.3 | G32: Financement approximatif
A34: GEOGRAPHIE
A35: Villes | B35: ='Inputs V2'!B21 -> 1 | C35: ='Inputs V2'!C21 -> 3 | D35: ='Inputs V2'!D21 -> 8 | E35: ='Inputs V2'!E21 -> 15 | F35: ='Inputs V2'!F21 -> 25 | G35: Expansion
A36: Partenaires / ville | B36: =B14/B35 -> 40 | C36: =C14/C35 -> 40 | D36: =D14/D35 -> 50 | E36: =E14/E35 -> 60 | F36: =F14/F35 -> 60 | G36: Densite moyenne
A37: ARR / ville | B37: =B23/B35 -> 22639.2 | C37: =C23/C35 -> 44725 | D37: =D23/D35 -> 69940.5 | E37: =E23/E35 -> 96684 | F37: =F23/F35 -> 120648 | G37: Qualite expansion

Sheet Dashboard V2
A1: ekho — Dashboard decisionnel V2
A3: Metric | B3: An 1 | C3: An 2 | D3: An 3 | E3: An 4 | F3: An 5
A4: CA annuel total | B4: ='Projections V2'!B23 -> 22639.2 | C4: ='Projections V2'!C23 -> 134175 | D4: ='Projections V2'!D23 -> 559524 | E4: ='Projections V2'!E23 -> 1450260 | F4: ='Projections V2'!F23 -> 3016200
A5: EBITDA | B5: ='Projections V2'!B31 -> -121409.48 | C5: ='Projections V2'!C31 -> -219515.25 | D5: ='Projections V2'!D31 -> -280100.6 | E5: ='Projections V2'!E31 -> -309355 | F5: ='Projections V2'!F31 -> -189690
A8: Decision | B8: Lecture
A9: Demarrer ? | B9: Oui, si la validation se fait ville par ville et pas en expansion prematuree.
A10: Priorite 1 | B10: Prouver que les utilisateurs decident plus vite ou aller.
A11: Priorite 2 | B11: Prouver que les lieux voient une valeur mesurable.
A12: Ne pas faire | B12: Monetiser le ranking des recommandations.
A13: Modifier la vision | B13: Passer de recommandation de lieux a carte vivante des moods et presences.
A14: Modifier le modele | B14: Ajouter churn, couts, besoin de cash, scenarios.
A15: Point dur | B15: Le Premium utilisateur ne doit pas etre le coeur du BP au depart.
A16: Go / No Go 90j | B16: Continuer si activation utilisateur + 10 lieux actifs + signaux recurrents.

Sheet Validation 0-90j
A1: ekho — Plan de validation avant acceleration
A3: Hypothese | B3: KPI | C3: Seuil 90 jours | D3: Signal positif | E3: Si ca echoue | F3: Priorite
A4: Les gens veulent une aide de decision | B4: % sessions avec action lieu | C4: >= 30% | D4: Sauvegarde, itineraire, appel, partage | E4: Simplifier onboarding / moods | F4: Haute
A5: La densite locale suffit | B5: Lieux partenaires coeur de zone | C5: >= 40 signes / 20 actifs | D5: Les lieux couvrent plusieurs usages | E5: Reduire zone, renforcer terrain | F5: Haute
A6: Les lieux jouent le jeu | B6: Partenaires actifs hebdo | C6: >= 10 | D6: Maj ambiance, event, horaire creuse | E6: Changer promesse B2B | F6: Haute
A7: La presence sociale cree de la valeur | B7: Opt-in presence anonyme | C7: >= 15% | D7: Utilisateurs acceptent signal discret | E7: Rendre plus rassurant / moins social | F7: Moyenne
A8: Le B2B peut payer | B8: Lieux prets a payer apres test | C8: >= 10 | D8: Interet pour stats/heures creuses | E8: Baisser prix ou revoir offre | F8: Haute
A9: L'app devient une habitude | B9: Retention D7 / D30 | C9: D7 >= 20%, D30 >= 8% | D9: Retour sans notification forcee | E9: Repenser frequence d'usage | F9: Haute
A10: La donnee devient proprietaire | B10: Signaux collectes/semaine | C10: >= 1000 | D10: Moods, choix, refus, affluence | E10: Ajouter friction utile de feedback | F10: Haute
